<?xml version='1.0' encoding='UTF-8'?>
<org.jfrog.hudson.ArtifactoryBuilder_-DescriptorImpl plugin="artifactory@2.13.1">
  <useCredentialsPlugin>false</useCredentialsPlugin>
  <pushToBintrayEnabled>true</pushToBintrayEnabled>
  <buildInfoProxyEnabled>false</buildInfoProxyEnabled>
  <buildInfoProxyPort>0</buildInfoProxyPort>
  <buildInfoProxyCertPublic>C:\Program Files (x86)\Jenkins\secrets\jfrog\certs\jfrog.proxy.crt</buildInfoProxyCertPublic>
  <buildInfoProxyCertPrivate>C:\Program Files (x86)\Jenkins\secrets\jfrog\certs\jfrog.proxy.key</buildInfoProxyCertPrivate>
</org.jfrog.hudson.ArtifactoryBuilder_-DescriptorImpl>